bamnado/__init__.py
bamnado/_bamnado.abi3.so
bamnado/_bamnado.pyi
bamnado/py.typed
bamnado-0.4.4.dist-info/METADATA
bamnado-0.4.4.dist-info/WHEEL
bamnado-0.4.4.dist-info/RECORD
