Metadata-Version: 2.4
Name: bamnado
Version: 0.4.4
Classifier: Programming Language :: Python :: 3
Classifier: Programming Language :: Python :: 3.10
Classifier: Programming Language :: Python :: 3.11
Classifier: Programming Language :: Python :: 3.12
Classifier: Programming Language :: Rust
Classifier: Topic :: Scientific/Engineering :: Bio-Informatics
Classifier: Operating System :: POSIX :: Linux
Classifier: Operating System :: MacOS :: MacOS X
Classifier: Operating System :: Microsoft :: Windows
Requires-Dist: numpy>=2
Requires-Dist: pytest>=7.0 ; extra == 'test'
Requires-Dist: pytest-cov>=4.0 ; extra == 'test'
Provides-Extra: test
Summary: Python bindings for BamNado
Keywords: bioinformatics,scATAC-seq,MCC,BAM
Home-Page: https://github.com/alsmith151/BamNado
Author-email: Alastair Smith <alastair.smith@ndcls.ox.ac.uk>
License: MIT OR Apache-2.0
Requires-Python: >=3.10
Project-URL: Documentation, https://alsmith151.github.io/BamNado/
Project-URL: Homepage, https://github.com/alsmith151/BamNado
Project-URL: Repository, https://github.com/alsmith151/BamNado
